{
  "Author": "ABagOfSunshine",
  "Name": "RPChatHighlights",
  "InternalName": "RPHighlight",
  "AssemblyVersion": "1.0.0",
  "Description": "Allows User To Color Text Surrounded By Astrisks Or Parenthesis",
  "ApplicableVersion": "any",
  "RepoUrl": "https://github.com/ABagOSunshine/RPChatHighlight",
  "Tags": [
    "highlight",
    "plugin",
    "rp",
    "roleplay",
    "chat"
  ],
  "DalamudApiLevel": 12,
  "LoadRequiredState": 0,
  "LoadSync": false,
  "CanUnloadAsync": false,
  "LoadPriority": 0,
  "IconUrl": "https://github.com/ABagOSunshine/RPChatHighlight/blob/6bedccca379e77823cbb44e3232e137980b1b947/Icon.png",
  "Punchline": "Highlights RolePlay Text",
  "AcceptsFeedback": true,
  "DownloadLinkInstall": "https://github.com/ABagOSunshine/RPChatHighlight/releases/download/v1.0.0/RPHPlugin.zip",
  "DownloadLinkTesting": "https://github.com/ABagOSunshine/RPChatHighlight/releases/download/v1.0.0/RPHPlugin.zip",
  "DownloadLinkUpdate": "https://github.com/ABagOSunshine/RPChatHighlight/releases/download/v1.0.0/RPHPlugin.zip"
}
